docker/Dockerfile
docker/build.sh
orca/__init__.py
orca/errors.py
orca/airflow/__init__.py
orca/airflow/provider_info.py
orca/services/__init__.py
orca/services/base/__init__.py
orca/services/base/client_factory.py
orca/services/base/config.py
orca/services/base/hook.py
orca/services/base/ops.py
orca/services/nextflowtower/__init__.py
orca/services/nextflowtower/client.py
orca/services/nextflowtower/client_factory.py
orca/services/nextflowtower/config.py
orca/services/nextflowtower/hook.py
orca/services/nextflowtower/models.py
orca/services/nextflowtower/ops.py
orca/services/nextflowtower/utils.py
orca/services/sevenbridges/__init__.py
orca/services/sevenbridges/client_factory.py
orca/services/sevenbridges/config.py
orca/services/sevenbridges/hook.py
orca/services/sevenbridges/models.py
orca/services/sevenbridges/ops.py
orca/services/synapse/__init__.py
orca/services/synapse/client_factory.py
orca/services/synapse/config.py
orca/services/synapse/hook.py
orca/services/synapse/ops.py
py_orca-1.5.2.dist-info/licenses/LICENSE.txt
py_orca-1.5.2.dist-info/METADATA
py_orca-1.5.2.dist-info/WHEEL
py_orca-1.5.2.dist-info/entry_points.txt
py_orca-1.5.2.dist-info/top_level.txt
py_orca-1.5.2.dist-info/RECORD
