Metadata-Version: 2.4
Name: py-orca
Version: 1.5.2
Summary: Python package for connecting services and building data pipelines
Home-page: https://github.com/Sage-Bionetworks-Workflows/py-orca
Author: Bruno Grande
Author-email: bruno.grande@sagebase.org
License: Apache-2.0
Project-URL: Source, https://github.com/Sage-Bionetworks-Workflows/py-orca
Project-URL: Tracker, https://github.com/Sage-Bionetworks-Workflows/py-orca/issues
Platform: any
Classifier: Development Status :: 4 - Beta
Classifier: Programming Language :: Python
Classifier: Framework :: Apache Airflow
Classifier: Framework :: Apache Airflow :: Provider
Requires-Python: <3.12,>=3.10
License-File: LICENSE.txt
Requires-Dist: apache-airflow==2.10.5
Requires-Dist: pydantic~=1.10
Requires-Dist: sqlalchemy<2.0
Requires-Dist: typing-extensions~=4.5
Provides-Extra: all
Requires-Dist: challengeutils~=4.3; extra == "all"
Requires-Dist: synapseclient~=4.8; extra == "all"
Requires-Dist: fs-synapse~=2.1; extra == "all"
Requires-Dist: sevenbridges-python~=2.9; extra == "all"
Requires-Dist: requests~=2.28; extra == "all"
Requires-Dist: urllib3<2.0; extra == "all"
Provides-Extra: testing
Requires-Dist: setuptools~=65.0; extra == "testing"
Requires-Dist: pytest~=7.0; extra == "testing"
Requires-Dist: pytest-cov~=4.0; extra == "testing"
Requires-Dist: pytest-mock~=3.0; extra == "testing"
Requires-Dist: pytest-dotenv~=0.5.2; extra == "testing"
Requires-Dist: pytest-asyncio~=0.21.0; extra == "testing"
Requires-Dist: pytest-xdist<3.0.0,>=2.2; extra == "testing"
Provides-Extra: dev
Requires-Dist: pre-commit~=2.0; extra == "dev"
Requires-Dist: sphinx-rtd-theme~=1.0; extra == "dev"
Requires-Dist: black~=22.0; extra == "dev"
Requires-Dist: flake8~=5.0; extra == "dev"
Requires-Dist: isort~=5.0; extra == "dev"
Requires-Dist: mypy~=1.0; extra == "dev"
Requires-Dist: flake8-pyproject~=1.0; extra == "dev"
Requires-Dist: sphinx-autodoc-typehints~=1.21; extra == "dev"
Requires-Dist: interrogate~=1.6; extra == "dev"
Requires-Dist: jupyterlab~=3.6; extra == "dev"
Requires-Dist: vulture~=2.7; extra == "dev"
Requires-Dist: autopep8~=2.0; extra == "dev"
Requires-Dist: typing-extensions~=4.5; extra == "dev"
Requires-Dist: metaflow~=2.9; extra == "dev"
Requires-Dist: s3fs~=2023.5; extra == "dev"
Dynamic: license-file
